{
    "objects": [
        {
            "attributes": {
                "description": "This dashboard provides expanded alerts overview for Azure cloud",
                "hits": 0,
                "kibanaSavedObjectMeta": {
                    "searchSourceJSON": "{\"query\": {\"query\": \"\", \"language\": \"kuery\"}, \"filter\": []}"
                },
                "optionsJSON": "{\"useMargins\": true, \"hidePanelTitles\": false}",
                "panelsJSON": "[{\"gridData\": {\"w\": 7, \"i\": \"9d1a26e6-2ff0-4d3e-bab3-7bb3c50cd060\", \"h\": 4, \"x\": 0, \"y\": 0}, \"embeddableConfig\": {\"title\": \"\"}, \"panelIndex\": \"9d1a26e6-2ff0-4d3e-bab3-7bb3c50cd060\", \"version\": \"7.4.0\", \"panelRefName\": \"panel_0\"}, {\"gridData\": {\"w\": 14, \"i\": \"676fd632-a9c1-46ed-829b-ca5b55817379\", \"h\": 4, \"x\": 7, \"y\": 0}, \"embeddableConfig\": {\"title\": \"\"}, \"panelIndex\": \"676fd632-a9c1-46ed-829b-ca5b55817379\", \"version\": \"7.4.0\", \"panelRefName\": \"panel_1\"}, {\"gridData\": {\"w\": 27, \"i\": \"096b4eaa-072e-455f-befa-3076f71be12d\", \"h\": 15, \"x\": 21, \"y\": 0}, \"embeddableConfig\": {}, \"panelIndex\": \"096b4eaa-072e-455f-befa-3076f71be12d\", \"version\": \"7.4.0\", \"panelRefName\": \"panel_2\"}, {\"gridData\": {\"w\": 27, \"i\": \"162fb43e-fff3-4f50-aa9b-a713418bd651\", \"h\": 9, \"x\": 21, \"y\": 15}, \"embeddableConfig\": {}, \"panelIndex\": \"162fb43e-fff3-4f50-aa9b-a713418bd651\", \"version\": \"7.4.0\", \"panelRefName\": \"panel_3\"}, {\"gridData\": {\"w\": 21, \"i\": \"36fb5c08-80d9-4a1c-8fde-9c063381fdd8\", \"h\": 20, \"x\": 0, \"y\": 4}, \"embeddableConfig\": {}, \"panelIndex\": \"36fb5c08-80d9-4a1c-8fde-9c063381fdd8\", \"version\": \"7.4.0\", \"panelRefName\": \"panel_4\"}]",
                "timeRestore": false,
                "title": "[Filebeat Azure] Alerts Overview",
                "version": 1
            },
            "id": "0f559cc0-f0d5-11e9-90ec-112a988266d5",
            "migrationVersion": {
                "dashboard": "7.3.0"
            },
            "references": [
                {
                    "id": "46544960-f0d5-11e9-90ec-112a988266d5",
                    "name": "panel_0",
                    "type": "visualization"
                },
                {
                    "id": "097d74d0-f044-11e9-90ec-112a988266d5",
                    "name": "panel_1",
                    "type": "visualization"
                },
                {
                    "id": "52c2a4e0-ec1f-11e9-90ec-112a988266d5",
                    "name": "panel_2",
                    "type": "visualization"
                },
                {
                    "id": "f684a750-ec23-11e9-90ec-112a988266d5",
                    "name": "panel_3",
                    "type": "visualization"
                },
                {
                    "id": "c704b050-f0de-11e9-90ec-112a988266d5",
                    "name": "panel_4",
                    "type": "visualization"
                }
            ],
            "type": "dashboard",
            "updated_at": "2019-10-18T15:21:16.305Z",
            "version": "WzkyNDEsMV0="
        },
        {
            "attributes": {
                "description": "",
                "kibanaSavedObjectMeta": {
                    "searchSourceJSON": "{\"query\": {\"query\": \"\", \"language\": \"kuery\"}, \"filter\": []}"
                },
                "title": "Navigation Alerts [Filebeat Azure]",
                "uiStateJSON": "{}",
                "version": 1,
                "visState": "{\"type\": \"markdown\", \"aggs\": [], \"params\": {\"fontSize\": 10, \"openLinksInNewTab\": false, \"markdown\": \"### Azure Monitoring\\n\\n[Overview](#/dashboard/41e84340-ec20-11e9-90ec-112a988266d5) | [Users](#/dashboard/87095750-f05a-11e9-90ec-112a988266d5) | [**Alerts**](#/dashboard/0f559cc0-f0d5-11e9-90ec-112a988266d5) \"}, \"title\": \"Navigation Alerts [Filebeat Azure]\"}"
            },
            "id": "46544960-f0d5-11e9-90ec-112a988266d5",
            "migrationVersion": {
                "visualization": "7.3.1"
            },
            "references": [],
            "type": "visualization",
            "updated_at": "2019-10-17T11:57:36.537Z",
            "version": "WzQ5NDAsMV0="
        },
        {
            "attributes": {
                "description": "",
                "kibanaSavedObjectMeta": {
                    "searchSourceJSON": "{\"query\": {\"query\": \"\", \"language\": \"kuery\"}, \"filter\": []}"
                },
                "title": "Subscriptions Filter [Filebeat Azure]",
                "uiStateJSON": "{}",
                "version": 1,
                "visState": "{\"type\": \"input_control_vis\", \"aggs\": [], \"params\": {\"pinFilters\": false, \"updateFiltersOnChange\": true, \"controls\": [{\"indexPatternRefName\": \"control_0_index_pattern\", \"parent\": \"\", \"fieldName\": \"azure.subscription_id\", \"id\": \"1571250866125\", \"options\": {\"order\": \"desc\", \"type\": \"terms\", \"multiselect\": true, \"size\": 5, \"dynamicOptions\": true}, \"type\": \"list\", \"label\": \"Subscription ID\"}], \"useTimeFilter\": false}, \"title\": \"Subscriptions Filter [Filebeat Azure]\"}"
            },
            "id": "097d74d0-f044-11e9-90ec-112a988266d5",
            "migrationVersion": {
                "visualization": "7.3.1"
            },
            "references": [
                {
                    "id": "filebeat-*",
                    "name": "control_0_index_pattern",
                    "type": "index-pattern"
                }
            ],
            "type": "visualization",
            "updated_at": "2019-10-16T18:37:41.917Z",
            "version": "WzQ0MDEsMV0="
        },
        {
            "attributes": {
                "description": "",
                "kibanaSavedObjectMeta": {
                    "searchSourceJSON": "{\"query\": {\"query\": \"\", \"language\": \"kuery\"}, \"filter\": []}"
                },
                "title": "Alerts Overview [Filebeat Azure]",
                "uiStateJSON": "{}",
                "version": 1,
                "visState": "{\"type\": \"metrics\", \"aggs\": [], \"params\": {\"series\": [{\"point_size\": 1, \"fill\": 0.5, \"line_width\": 1, \"hide_in_legend\": 0, \"color\": \"rgba(252,220,0,1)\", \"metrics\": [{\"type\": \"count\", \"id\": \"61ca57f2-469d-11e7-af02-69e470af7417\"}], \"formatter\": \"number\", \"stacked\": \"none\", \"filter\": {\"query\": \"event.outcome: \\\"Activated\\\"\", \"language\": \"kuery\"}, \"axis_position\": \"right\", \"separate_axis\": 0, \"chart_type\": \"line\", \"id\": \"61ca57f1-469d-11e7-af02-69e470af7417\", \"split_mode\": \"filter\"}, {\"point_size\": 1, \"fill\": 0.5, \"line_width\": 1, \"hide_in_legend\": 0, \"color\": \"#68BC00\", \"metrics\": [{\"type\": \"count\", \"id\": \"5a52f171-ec1e-11e9-b6a7-21d19b63822a\"}], \"formatter\": \"number\", \"stacked\": \"none\", \"filter\": {\"query\": \"event.outcome: \\\"Resolved\\\" or event.outcome: \\\"Succeeded\\\"\", \"language\": \"kuery\"}, \"axis_position\": \"right\", \"separate_axis\": 0, \"chart_type\": \"line\", \"id\": \"5a52f170-ec1e-11e9-b6a7-21d19b63822a\", \"split_mode\": \"filter\"}], \"show_grid\": 1, \"axis_formatter\": \"number\", \"default_index_pattern\": \"metricbeat-*\", \"filter\": {\"query\": \"event.dataset :\\\"azure.activitylogs\\\" and event.category : \\\"Alert\\\"\", \"language\": \"kuery\"}, \"index_pattern\": \"filebeat-*\", \"time_field\": \"\", \"axis_position\": \"left\", \"axis_scale\": \"normal\", \"interval\": \"\", \"id\": \"61ca57f0-469d-11e7-af02-69e470af7417\", \"show_legend\": 0, \"isModelInvalid\": false, \"type\": \"timeseries\", \"default_timefield\": \"@timestamp\"}, \"title\": \"Alerts Overview [Filebeat Azure]\"}"
            },
            "id": "52c2a4e0-ec1f-11e9-90ec-112a988266d5",
            "migrationVersion": {
                "visualization": "7.3.1"
            },
            "references": [],
            "type": "visualization",
            "updated_at": "2019-10-16T18:41:58.846Z",
            "version": "WzQ0MDcsMV0="
        },
        {
            "attributes": {
                "description": "",
                "kibanaSavedObjectMeta": {
                    "searchSourceJSON": "{\"indexRefName\": \"kibanaSavedObjectMeta.searchSourceJSON.index\", \"query\": {\"query\": \"event.dataset :\\\"azure.activitylogs\\\" and event.category : \\\"Alert\\\" \", \"language\": \"kuery\"}, \"filter\": []}"
                },
                "title": "Alerts Count [Filebeat Azure]",
                "uiStateJSON": "{}",
                "version": 1,
                "visState": "{\"type\": \"metric\", \"aggs\": [{\"schema\": \"metric\", \"type\": \"count\", \"params\": {\"customLabel\": \"Alerts\"}, \"enabled\": true, \"id\": \"1\"}, {\"schema\": \"group\", \"type\": \"filters\", \"params\": {\"filters\": [{\"input\": {\"query\": \"event.outcome : \\\"Activated\\\"\", \"language\": \"kuery\"}, \"label\": \"Activated\"}, {\"input\": {\"query\": \"event.outcome : \\\"Resolved\\\"\", \"language\": \"kuery\"}, \"label\": \"Resolved\"}, {\"input\": {\"query\": \"event.outcome : \\\"Succeeded\\\"\", \"language\": \"kuery\"}, \"label\": \"Succeeded\"}]}, \"enabled\": true, \"id\": \"2\"}], \"params\": {\"addTooltip\": true, \"addLegend\": false, \"type\": \"metric\", \"dimensions\": {\"bucket\": {\"type\": \"vis_dimension\", \"accessor\": 0, \"format\": {\"params\": {}, \"id\": \"string\"}}, \"metrics\": [{\"type\": \"vis_dimension\", \"accessor\": 1, \"format\": {\"params\": {}, \"id\": \"number\"}}]}, \"metric\": {\"metricColorMode\": \"None\", \"style\": {\"bgFill\": \"#000\", \"fontSize\": 60, \"labelColor\": false, \"bgColor\": false, \"subText\": \"\"}, \"colorsRange\": [{\"from\": 0, \"type\": \"range\", \"to\": 10000}], \"colorSchema\": \"Green to Red\", \"invertColors\": false, \"percentageMode\": false, \"useRanges\": false, \"labels\": {\"show\": true}}}, \"title\": \"Alerts Count [Filebeat Azure]\"}"
            },
            "id": "f684a750-ec23-11e9-90ec-112a988266d5",
            "migrationVersion": {
                "visualization": "7.3.1"
            },
            "references": [
                {
                    "id": "filebeat-*",
                    "name": "kibanaSavedObjectMeta.searchSourceJSON.index",
                    "type": "index-pattern"
                }
            ],
            "type": "visualization",
            "updated_at": "2019-10-16T18:44:12.955Z",
            "version": "WzQ0MTAsMV0="
        },
        {
            "attributes": {
                "description": "",
                "kibanaSavedObjectMeta": {
                    "searchSourceJSON": "{\"indexRefName\": \"kibanaSavedObjectMeta.searchSourceJSON.index\", \"query\": {\"query\": \"event.dataset :\\\"azure.activitylogs\\\" and event.category : \\\"Alert\\\" \", \"language\": \"kuery\"}, \"filter\": []}"
                },
                "title": "Alerts Heatmap [Filebeat Azure]",
                "uiStateJSON": "{\"vis\": {\"defaultColors\": {\"0\": \"rgb(247,252,245)\"}}}",
                "version": 1,
                "visState": "{\"type\": \"heatmap\", \"aggs\": [{\"schema\": \"metric\", \"type\": \"count\", \"params\": {}, \"enabled\": true, \"id\": \"1\"}, {\"schema\": \"segment\", \"type\": \"terms\", \"params\": {\"otherBucketLabel\": \"Other\", \"orderBy\": \"1\", \"size\": 5, \"otherBucket\": false, \"order\": \"desc\", \"field\": \"azure.resource.provider\", \"customLabel\": \"Provider\", \"missingBucket\": false, \"missingBucketLabel\": \"Missing\"}, \"enabled\": true, \"id\": \"2\"}, {\"schema\": \"group\", \"type\": \"terms\", \"params\": {\"otherBucketLabel\": \"Other\", \"orderBy\": \"1\", \"size\": 5, \"otherBucket\": false, \"order\": \"desc\", \"field\": \"azure.resource.group\", \"customLabel\": \"Resource Group\", \"missingBucket\": false, \"missingBucketLabel\": \"Missing\"}, \"enabled\": true, \"id\": \"3\"}], \"params\": {\"setColorRange\": false, \"valueAxes\": [{\"scale\": {\"type\": \"linear\", \"defaultYExtents\": false}, \"type\": \"value\", \"show\": false, \"id\": \"ValueAxis-1\", \"labels\": {\"color\": \"black\", \"show\": false, \"overwriteColor\": false, \"rotate\": 0}}], \"enableHover\": false, \"colorsRange\": [], \"addTooltip\": true, \"invertColors\": false, \"percentageMode\": false, \"times\": [], \"addLegend\": true, \"colorSchema\": \"Greens\", \"legendPosition\": \"right\", \"type\": \"heatmap\", \"colorsNumber\": 4, \"dimensions\": {\"x\": {\"accessor\": 0, \"params\": {}, \"aggType\": \"terms\", \"format\": {\"params\": {\"otherBucketLabel\": \"Other\", \"id\": \"string\", \"missingBucketLabel\": \"Missing\"}, \"id\": \"terms\"}}, \"y\": [{\"accessor\": 1, \"params\": {}, \"aggType\": \"count\", \"format\": {\"id\": \"number\"}}]}}, \"title\": \"Alerts Heatmap [Filebeat Azure]\"}"
            },
            "id": "c704b050-f0de-11e9-90ec-112a988266d5",
            "migrationVersion": {
                "visualization": "7.3.1"
            },
            "references": [
                {
                    "id": "filebeat-*",
                    "name": "kibanaSavedObjectMeta.searchSourceJSON.index",
                    "type": "index-pattern"
                }
            ],
            "type": "visualization",
            "updated_at": "2019-10-17T13:05:22.389Z",
            "version": "WzQ5NTYsMV0="
        }
    ],
    "version": "7.4.0"
}